universal_response_mobile_api/__init__.py
universal_response_mobile_api/errors.py
universal_response_mobile_api/json.py
universal_response_mobile_api-0.1.9.dist-info/LICENSE
universal_response_mobile_api-0.1.9.dist-info/METADATA
universal_response_mobile_api-0.1.9.dist-info/WHEEL
universal_response_mobile_api-0.1.9.dist-info/top_level.txt
universal_response_mobile_api-0.1.9.dist-info/RECORD
